dons/__init__.py
dons-0.0.1.dist-info/LICENSE
dons-0.0.1.dist-info/METADATA
dons-0.0.1.dist-info/WHEEL
dons-0.0.1.dist-info/top_level.txt
dons-0.0.1.dist-info/RECORD
