Metadata-Version: 2.1
Name: dons
Version: 0.0.1
Summary: Dons
Home-page: https://github.com/MDAddario/dons
Author: Michael Lindner-D'Addario
Author-email: michael.lindner.daddario@gmail.com
License: UNKNOWN
Platform: UNKNOWN
Classifier: Programming Language :: Python :: 3
Classifier: License :: OSI Approved :: MIT License
Classifier: Operating System :: OS Independent
Requires-Python: >=3.6
